COPYING
COPYRIGHT
MANIFEST.in
README.md
RELEASE_NOTES.md
requirements.txt
requirements_dev.txt
setup.py
craw/__init__.py
craw/annotation.py
craw/argparse_util.py
craw/coverage.py
craw/heatmap.py
craw/util.py
craw/wig.py
craw.egg-info/PKG-INFO
craw.egg-info/SOURCES.txt
craw.egg-info/dependency_links.txt
craw.egg-info/entry_points.txt
craw.egg-info/requires.txt
craw.egg-info/top_level.txt
craw/scripts/__init__.py
craw/scripts/craw_coverage.py
craw/scripts/craw_htmp.py
doc/build/html/.buildinfo
doc/build/html/annotation.html
doc/build/html/argparse_util.html
doc/build/html/coverage.html
doc/build/html/craw.html
doc/build/html/craw_coverage.html
doc/build/html/craw_htmp.html
doc/build/html/genindex.html
doc/build/html/heatmap.html
doc/build/html/index.html
doc/build/html/inputs-outputs.html
doc/build/html/installation.html
doc/build/html/objects.inv
doc/build/html/overview.html
doc/build/html/py-modindex.html
doc/build/html/quickstart.html
doc/build/html/release_notes.html
doc/build/html/search.html
doc/build/html/searchindex.js
doc/build/html/wig.html
doc/build/html/_images/annotation_file.png
doc/build/html/_images/coverage_matrix.png
doc/build/html/_images/craw_htmp_sense_on_left.png
doc/build/html/_images/craw_htmp_sense_on_top.png
doc/build/html/_images/craw_window.png
doc/build/html/_images/craw_window_before_after.png
doc/build/html/_images/craw_window_variable.png
doc/build/html/_images/genome.png
doc/build/html/_images/norm_demo_lin.png
doc/build/html/_images/norm_demo_log.png
doc/build/html/_images/norm_demo_row+log.png
doc/build/html/_images/norm_demo_row.png
doc/build/html/_images/spacer.png
doc/build/html/_images/wte1_0+2000_mark.png
doc/build/html/_modules/collections.html
doc/build/html/_modules/craw.html
doc/build/html/_modules/index.html
doc/build/html/_modules/craw/annotation.html
doc/build/html/_modules/craw/argparse_util.html
doc/build/html/_modules/craw/coverage.html
doc/build/html/_modules/craw/heatmap.html
doc/build/html/_modules/craw/wig.html
doc/build/html/_modules/craw/scripts/craw_coverage.html
doc/build/html/_modules/craw/scripts/craw_htmp.html
doc/build/html/_sources/annotation.rst.txt
