Metadata-Version: 2.1
Name: craw
Version: 1.0.0
Summary: Counter RNA seq Window is a package which aim to compute and visualize the coverage of RNA seq experiment.
Home-page: https://gitlab.pasteur.fr/bneron/craw
Author: Bertrand Neron
Author-email: bneron@pasteur.fr
License: UNKNOWN
Keywords: bioinformatics,RNAseq,coverage
Platform: Unix
Classifier: Development Status :: 5 - Production/Stable
Classifier: Environment :: Console
Classifier: Intended Audience :: Science/Research
Classifier: Operating System :: Unix
Classifier: Programming Language :: Python :: 3 :: Only
Classifier: Topic :: Scientific/Engineering :: Bio-Informatics
Classifier: License :: OSI Approved :: GNU General Public License v3 (GPLv3)
Requires-Python: >=3.5
Provides-Extra: dev
